HISTORY.rst
LICENSE
MANIFEST.in
README.rst
setup.py
django_notifyme_by_email.egg-info/PKG-INFO
django_notifyme_by_email.egg-info/SOURCES.txt
django_notifyme_by_email.egg-info/dependency_links.txt
django_notifyme_by_email.egg-info/not-zip-safe
django_notifyme_by_email.egg-info/top_level.txt
notifyme_by_email/__init__.py
notifyme_by_email/delivery_backends.py
notifyme_by_email/templates/notifyme/notification_types/generic/email/body.html
notifyme_by_email/templates/notifyme/notification_types/generic/email/body.txt
notifyme_by_email/templates/notifyme/notification_types/generic/email/subject.txt